CHANGES.txt
CONTRIBUTORS.txt
README.rst
bootstrap.py
buildout.cfg
setup.py
collective/__init__.py
collective.recipe.jenkinsjob.egg-info/PKG-INFO
collective.recipe.jenkinsjob.egg-info/SOURCES.txt
collective.recipe.jenkinsjob.egg-info/dependency_links.txt
collective.recipe.jenkinsjob.egg-info/entry_points.txt
collective.recipe.jenkinsjob.egg-info/namespace_packages.txt
collective.recipe.jenkinsjob.egg-info/not-zip-safe
collective.recipe.jenkinsjob.egg-info/requires.txt
collective.recipe.jenkinsjob.egg-info/top_level.txt
collective/recipe/__init__.py
collective/recipe/jenkinsjob/__init__.py
collective/recipe/jenkinsjob/tests/__init__.py
collective/recipe/jenkinsjob/tests/test_docs.py
docs/LICENSE.GPL
docs/LICENSE.ZPL
docs/LICENSE.txt