Metadata-Version: 1.0
Name: collective.recipe.jenkinsjob
Version: 1.0-alpha1
Summary: Buildout recipe to manage jobs on a remote Jenkins CI server.
Home-page: https://github.com/tisto/collective.recipe.jenkinsjob
Author: Domen Kožar and Timo Stollenwerk
Author-email: domen@dev.si
License: gpl
Platform: UNKNOWN
Classifier: Framework :: Buildout
Classifier: Intended Audience :: Developers
Classifier: Topic :: Software Development :: Build Tools
